{
    "type": "Feature",
    "id": "way/323099626",
    "properties": {
        "type": "way",
        "id": 323099626,
        "tags": {
            "intermittent": "yes",
            "natural": "water",
            "source": "Bing",
            "water": "pond"
        },
        "relations": [],
        "meta": {}
    },
    "geometry": {
        "type": "Polygon",
        "coordinates": [
            [
                [
                    -110.9241237,
                    38.0634955
                ],
                [
                    -110.9241022,
                    38.0634741
                ],
                [
                    -110.9240198,
                    38.0634901
                ],
                [
                    -110.9240062,
                    38.0635364
                ],
                [
                    -110.9239915,
                    38.0636191
                ],
                [
                    -110.9239554,
                    38.0637197
                ],
                [
                    -110.9239746,
                    38.0638282
                ],
                [
                    -110.9240864,
                    38.0638469
                ],
                [
                    -110.9241768,
                    38.0638157
                ],
                [
                    -110.9241994,
                    38.0637099
                ],
                [
                    -110.9241531,
                    38.0636707
                ],
                [
                    -110.9241667,
                    38.0635755
                ],
                [
                    -110.9241237,
                    38.0634955
                ]
            ]
        ]
    }
}