{
    "type": "Feature",
    "id": "way/144720416",
    "properties": {
        "type": "way",
        "id": 144720416,
        "tags": {
            "highway": "track",
            "source": "Bing",
            "surface": "unpaved",
            "tracktype": "grade3"
        },
        "relations": [],
        "meta": {}
    },
    "geometry": {
        "type": "LineString",
        "coordinates": [
            [
                -111.0739474,
                38.0767228
            ],
            [
                -111.0740309,
                38.0766068
            ],
            [
                -111.0740358,
                38.0764675
            ],
            [
                -111.0739621,
                38.0762277
            ],
            [
                -111.0739326,
                38.0760034
            ],
            [
                -111.0740457,
                38.07581
            ],
            [
                -111.0744338,
                38.0755547
            ],
            [
                -111.0749301,
                38.0752491
            ],
            [
                -111.075338,
                38.0752414
            ]
        ]
    }
}