{
    "type": "Feature",
    "id": "way/145433807",
    "properties": {
        "type": "way",
        "id": 145433807,
        "tags": {
            "highway": "track",
            "source": "Bing",
            "surface": "dirt",
            "tracktype": "grade5"
        },
        "relations": [],
        "meta": {}
    },
    "geometry": {
        "type": "LineString",
        "coordinates": [
            [
                -110.7053468,
                37.8449474
            ],
            [
                -110.7054784,
                37.8446355
            ],
            [
                -110.7054297,
                37.8442159
            ],
            [
                -110.7054345,
                37.8433536
            ],
            [
                -110.7055174,
                37.8428069
            ],
            [
                -110.7054882,
                37.8425566
            ],
            [
                -110.7054004,
                37.8423949
            ],
            [
                -110.7052688,
                37.8420446
            ]
        ]
    }
}