{
    "type": "Feature",
    "id": "way/146472674",
    "properties": {
        "type": "way",
        "id": 146472674,
        "tags": {
            "highway": "track",
            "source": "Bing",
            "surface": "dirt",
            "tracktype": "grade4"
        },
        "relations": [],
        "meta": {}
    },
    "geometry": {
        "type": "LineString",
        "coordinates": [
            [
                -110.6443847,
                37.8956963
            ],
            [
                -110.6445086,
                37.895983
            ],
            [
                -110.644577,
                37.8963979
            ],
            [
                -110.644483,
                37.8968803
            ],
            [
                -110.6440256,
                37.8975077
            ],
            [
                -110.643876,
                37.89799
            ],
            [
                -110.6438931,
                37.8981283
            ],
            [
                -110.6440256,
                37.8982329
            ],
            [
                -110.6442008,
                37.8983307
            ],
            [
                -110.6443334,
                37.8985567
            ],
            [
                -110.6443462,
                37.8987186
            ],
            [
                -110.6443034,
                37.898921
            ],
            [
                -110.6439572,
                37.8993999
            ],
            [
                -110.6434528,
                37.8999733
            ],
            [
                -110.6433374,
                37.9002364
            ]
        ]
    }
}