{
    "type": "Feature",
    "id": "way/323163271",
    "properties": {
        "type": "way",
        "id": 323163271,
        "tags": {
            "intermittent": "yes",
            "natural": "water",
            "source": "Bing"
        },
        "relations": [],
        "meta": {}
    },
    "geometry": {
        "type": "Polygon",
        "coordinates": [
            [
                [
                    -111.0375475,
                    38.0781913
                ],
                [
                    -111.0374918,
                    38.078202
                ],
                [
                    -111.0374456,
                    38.0782287
                ],
                [
                    -111.0374158,
                    38.0782673
                ],
                [
                    -111.0374071,
                    38.0783119
                ],
                [
                    -111.0374208,
                    38.0783557
                ],
                [
                    -111.0374547,
                    38.0783921
                ],
                [
                    -111.0375037,
                    38.0784155
                ],
                [
                    -111.0375604,
                    38.0784224
                ],
                [
                    -111.037616,
                    38.0784116
                ],
                [
                    -111.0376623,
                    38.0783849
                ],
                [
                    -111.037692,
                    38.0783464
                ],
                [
                    -111.0377007,
                    38.0783018
                ],
                [
                    -111.0376871,
                    38.0782579
                ],
                [
                    -111.0376532,
                    38.0782215
                ],
                [
                    -111.0376042,
                    38.0781981
                ],
                [
                    -111.0375475,
                    38.0781913
                ]
            ]
        ]
    }
}