{
    "type": "Feature",
    "id": "way/146467118",
    "properties": {
        "type": "way",
        "id": 146467118,
        "tags": {
            "highway": "track",
            "source": "Bing",
            "surface": "dirt",
            "tracktype": "grade5"
        },
        "relations": [],
        "meta": {}
    },
    "geometry": {
        "type": "LineString",
        "coordinates": [
            [
                -110.6486703,
                37.8846323
            ],
            [
                -110.6487301,
                37.8845265
            ],
            [
                -110.6487592,
                37.884324
            ],
            [
                -110.6487505,
                37.883949
            ],
            [
                -110.6488,
                37.8838317
            ],
            [
                -110.6488992,
                37.8837857
            ],
            [
                -110.6491382,
                37.8837788
            ],
            [
                -110.6493685,
                37.8838018
            ],
            [
                -110.649625,
                37.8838754
            ],
            [
                -110.6500273,
                37.8840065
            ],
            [
                -110.65038,
                37.8840295
            ],
            [
                -110.6505899,
                37.8840088
            ],
            [
                -110.6507735,
                37.8839513
            ],
            [
                -110.650998,
                37.8839605
            ],
            [
                -110.6516101,
                37.8841538
            ],
            [
                -110.6527295,
                37.8843838
            ],
            [
                -110.6532017,
                37.88437
            ],
            [
                -110.6537643,
                37.8845127
            ],
            [
                -110.6539363,
                37.8846162
            ],
            [
                -110.6541025,
                37.8846714
            ],
            [
                -110.6544902,
                37.8847451
            ],
            [
                -110.6557057,
                37.8848624
            ],
            [
                -110.6560264,
                37.8849843
            ],
            [
                -110.6562654,
                37.8850027
            ],
            [
                -110.6565482,
                37.8849774
            ],
            [
                -110.6571457,
                37.8847358
            ],
            [
                -110.6573498,
                37.8846806
            ],
            [
                -110.6574314,
                37.8845932
            ],
            [
                -110.6575771,
                37.8845679
            ],
            [
                -110.6577287,
                37.8844943
            ],
            [
                -110.6579328,
                37.8842067
            ],
            [
                -110.6580727,
                37.8841285
            ],
            [
                -110.6582826,
                37.8840664
            ],
            [
                -110.6584079,
                37.8839628
            ],
            [
                -110.6584895,
                37.8837673
            ],
            [
                -110.6586295,
                37.8836545
            ]
        ]
    }
}